{
    "proj_1753892536_9899": {
        "name": "Teste criaçao com tamplate modificado",
        "description": "teste",
        "project_type": "outros",
        "document_template": "teste",
        "client_id": "6887cdaf0cf3a8.51328972",
        "analyst_id": "rafael",
        "status": "ativo",
        "priority": "media",
        "deadline": "2025-07-31",
        "workflow_stage": 5,
        "created_by": "admin",
        "created_at": "2025-07-30 16:22:16",
        "updated_at": "2025-08-06 18:06:21",
        "id": "proj_1753892536_9899"
    },
    "proj_1753979150_9736": {
        "name": "Projeto Teste ",
        "description": "esse é um projeto teste com numero de orçamento.",
        "budget_number": "1111.1111.V2",
        "project_type": "residencial",
        "document_template": "rg_teste___teste",
        "client_id": "6887cdaf0cf3a8.51328972",
        "analyst_id": "6887cb7c384b75.22527396",
        "status": "pendente",
        "priority": "alta",
        "deadline": "2025-08-09",
        "workflow_stage": 1,
        "created_by": "admin",
        "created_at": "2025-07-31 16:25:50",
        "updated_at": "2025-08-06 18:08:53",
        "id": "proj_1753979150_9736"
    },
    "proj_1754498260_4698": {
        "name": "Teste criaçao com tamplate modificado2",
        "description": "Teste criaçao com tamplate modificado2",
        "budget_number": "2024.2012.V2",
        "project_type": "residencial",
        "document_template": "rg_teste___teste",
        "client_id": "6887cdaf0cf3a8.51328972",
        "analyst_id": "6887cb7c384b75.22527396",
        "status": "pendente",
        "priority": "alta",
        "deadline": "2025-08-13",
        "workflow_stage": "documentos",
        "created_by": "admin",
        "created_at": "2025-08-06 16:37:40",
        "updated_at": "2025-08-06 16:37:40",
        "id": "proj_1754498260_4698"
    },
    "proj_1754499185_5348": {
        "name": "Teste criaçao com tamplate modificado2",
        "description": "teste Teste criaçao com tamplate modificado2",
        "budget_number": "2024.2012.V2",
        "project_type": "comercial",
        "document_template": "rg_teste___teste",
        "client_id": "6887cdaf0cf3a8.51328972",
        "analyst_id": "6887cb7c384b75.22527396",
        "status": "pendente",
        "priority": "media",
        "deadline": "2025-08-13",
        "workflow_stage": "documentos",
        "created_by": "admin",
        "created_at": "2025-08-06 16:53:05",
        "updated_at": "2025-08-06 16:53:05",
        "id": "proj_1754499185_5348"
    }
}